LICENSE
MANIFEST.in
README.rst
setup.py
django_indigorestwrapper.egg-info/PKG-INFO
django_indigorestwrapper.egg-info/SOURCES.txt
django_indigorestwrapper.egg-info/dependency_links.txt
django_indigorestwrapper.egg-info/top_level.txt
indigorestwrapper/__init__.py
indigorestwrapper/admin.py
indigorestwrapper/apps.py
indigorestwrapper/models.py
indigorestwrapper/serializers.py
indigorestwrapper/tests.py
indigorestwrapper/urls.py
indigorestwrapper/views.py
indigorestwrapper/management/__init__.py
indigorestwrapper/management/commands/__init__.py
indigorestwrapper/management/commands/updateindigodb.py
indigorestwrapper/migrations/0001_initial.py
indigorestwrapper/migrations/__init__.py