Metadata-Version: 1.1
Name: django-indigorestwrapper
Version: 0.6
Summary: This is a (completely unauthorized) REST wrapper for the Indigo home automation application, using Django and Django-rest-framework.
Home-page: https://github.com/EdwardMoyse/django-indigorestwrapper
Author: Edward Moyse
Author-email: edward.moyse@gmail.com
License: MIT License
Platform: UNKNOWN
Classifier: Environment :: Web Environment
Classifier: Framework :: Django
Classifier: Framework :: Django :: 1.9
Classifier: Intended Audience :: Developers
Classifier: License :: OSI Approved :: MIT License
Classifier: Operating System :: OS Independent
Classifier: Programming Language :: Python
Classifier: Programming Language :: Python :: 2
Classifier: Topic :: Internet :: WWW/HTTP
Classifier: Topic :: Internet :: WWW/HTTP :: Dynamic Content
